{
	"configurations" : 
	[
		{
			"abstractTargets" : 
			[
				{
					"directoryIndex" : 0,
					"id" : "nlohmann_json::@6890427a1f51a3e7e1df",
					"jsonFile" : "target-nlohmann_json-Debug-dfefde4e2d142e7a6a74.json",
					"name" : "nlohmann_json",
					"projectIndex" : 0
				},
				{
					"directoryIndex" : 0,
					"id" : "nlohmann_json::nlohmann_json::@6890427a1f51a3e7e1df",
					"jsonFile" : "target-nlohmann_json__nlohmann_json-Debug-99a73c2b70a50143b8f9.json",
					"name" : "nlohmann_json::nlohmann_json",
					"projectIndex" : 0
				}
			],
			"directories" : 
			[
				{
					"abstractTargetIndexes" : 
					[
						0,
						1
					],
					"build" : ".",
					"jsonFile" : "directory-.-Debug-f6f22219c74102c3da70.json",
					"minimumCMakeVersion" : 
					{
						"string" : "3.10"
					},
					"projectIndex" : 0,
					"source" : ".",
					"targetIndexes" : 
					[
						0
					]
				}
			],
			"name" : "Debug",
			"projects" : 
			[
				{
					"abstractTargetIndexes" : 
					[
						0,
						1
					],
					"directoryIndexes" : 
					[
						0
					],
					"name" : "NexusStreamCruncher",
					"targetIndexes" : 
					[
						0
					]
				}
			],
			"targets" : 
			[
				{
					"directoryIndex" : 0,
					"id" : "nexus_cruncher::@6890427a1f51a3e7e1df",
					"jsonFile" : "target-nexus_cruncher-Debug-4205fa1010cda2861ea2.json",
					"name" : "nexus_cruncher",
					"projectIndex" : 0
				}
			]
		}
	],
	"kind" : "codemodel",
	"paths" : 
	{
		"build" : "C:/Users/786/Desktop/Nexus-Stream/build",
		"source" : "C:/Users/786/Desktop/Nexus-Stream/cruncher"
	},
	"version" : 
	{
		"major" : 2,
		"minor" : 9
	}
}
